<?xml version="1.0" encoding="utf-8"?>
<publishData>
  <publishProfile publishUrl="C:\Publish\NExtra.Demo" deleteExistingFiles="True" ftpAnonymousLogin="False" ftpPassiveMode="True" msdeploySite="" msdeploySiteID="" msdeployRemoteSitePhysicalPath="" msdeployAllowUntrustedCertificate="False" msdeploySkipExtraFilesOnServer="True" msdeployMarkAsApp="False" profileName="Profile1" publishMethod="FileSystem" replaceMatchingFiles="False" userName="" savePWD="False" userPWD="" SelectedForPublish="True">
    <file relUrl="Scripts/Components/jquery.watermark-3.0.6/readme.txt" publishTime="10/04/2011 22:47:07" />
    <file relUrl="Views/Demo/NExtra.Testing.MetadataTypeRegistrator.cshtml" publishTime="10/04/2011 22:47:07" />
    <file relUrl="Content/Images/tick.png" publishTime="10/04/2011 22:47:07" />
    <file relUrl="Views/Demo/NExtra.Web.Testing.FakeMembershipUser.cshtml" publishTime="10/04/2011 22:47:07" />
    <file relUrl="Scripts/Components/jquery.treeview/images/plus.gif" publishTime="10/04/2011 22:47:07" />
    <file relUrl="Views/Demo/NExtra.ValidationAttributes.MinLengthAttribute.cshtml" publishTime="10/04/2011 22:47:07" />
    <file relUrl="Views/Demo/NExtra.Geo.DistanceConverter.cshtml" publishTime="10/04/2011 22:47:07" />
    <file relUrl="Scripts/Components/jquery.treeview/images/folder.gif" publishTime="10/04/2011 22:47:07" />
    <file relUrl="Views/Demo/NExtra.IO.FileSizePresenter.cshtml" publishTime="10/04/2011 22:47:07" />
    <file relUrl="Views/Demo/NExtra.Extensions.StringExtensions.cshtml" publishTime="10/04/2011 22:47:07" />
    <file relUrl="Web.config" publishTime="10/20/2011 00:22:51" />
    <file relUrl="Views/Demo/NExtra.Extensions.DateTimeExtensions.cshtml" publishTime="10/04/2011 22:47:07" />
    <file relUrl="Views/Demo/NExtra.Documentation.XmlDocumentationHandler_MemberInfo.cshtml" publishTime="10/04/2011 22:47:07" />
    <file relUrl="Views/Web.config" publishTime="10/04/2011 22:47:07" />
    <file relUrl="Views/Demo/NExtra.Extensions.AssemblyExtensions.cshtml" publishTime="10/04/2011 22:47:07" />
    <file relUrl="Scripts/jquery.validate.js" publishTime="10/04/2011 22:47:07" />
    <file relUrl="Views/Demo/NExtra.Web.Html5ElementConverter.cshtml" publishTime="10/04/2011 22:47:07" />
    <file relUrl="Views/Home/App_LocalResources/Index.cshtml.resx" publishTime="10/04/2011 22:47:07" />
    <file relUrl="Content/Css/elements.css" publishTime="10/04/2011 22:47:07" />
    <file relUrl="Views/Demo/NExtra.Web.Security.RolesFacade.cshtml" publishTime="10/04/2011 22:47:07" />
    <file relUrl="Views/Demo/App_LocalResources/NExtra.Mvc.HtmlHelpers.LocalResourceHelper.cshtml.resx" publishTime="10/04/2011 22:47:07" />
    <file relUrl="Views/Demo/NExtra.Geo.DistanceUnit.cshtml" publishTime="10/04/2011 22:47:07" />
    <file relUrl="Views/Demo/NExtra.Facades.FacadeBase.cshtml" publishTime="10/04/2011 22:47:07" />
    <file relUrl="bin/NExtra.Mvc.pdb" publishTime="10/19/2011 22:59:12" />
    <file relUrl="bin/NExtra.Demo.dll" publishTime="10/20/2011 00:02:38" />
    <file relUrl="Views/Demo/NExtra.ValidationAttributes.IpAddressAttribute.cshtml" publishTime="10/04/2011 22:47:07" />
    <file relUrl="Views/Demo/NExtra.Extensions.IntExtensions.cshtml" publishTime="10/04/2011 22:47:07" />
    <file relUrl="Views/Shared/Error.cshtml" publishTime="10/04/2011 22:47:07" />
    <file relUrl="Scripts/MicrosoftAjax.js" publishTime="10/04/2011 22:47:07" />
    <file relUrl="Content/Images/ul-clean-sep-bg.png" publishTime="10/04/2011 22:47:07" />
    <file relUrl="Scripts/Components/jquery.treeview/images/treeview-gray.gif" publishTime="10/04/2011 22:47:07" />
    <file relUrl="Scripts/Components/jquery.treeview/demo/async.html" publishTime="10/04/2011 22:47:07" />
    <file relUrl="Views/Demo/NExtra.ValidationAttributes.SwedishPostalCodeAttribute.cshtml" publishTime="10/04/2011 22:47:07" />
    <file relUrl="Content/Images/a-hover-bg.png" publishTime="10/04/2011 22:47:07" />
    <file relUrl="Scripts/Components/jquery.treeview/images/treeview-red-line.gif" publishTime="10/04/2011 22:47:07" />
    <file relUrl="Views/Demo/NExtra.Email.EmailSender.cshtml" publishTime="10/04/2011 22:47:07" />
    <file relUrl="Scripts/Components/jquery.treeview/images/minus.gif" publishTime="10/04/2011 22:47:07" />
    <file relUrl="Scripts/MicrosoftMvcAjax.debug.js" publishTime="10/04/2011 22:47:07" />
    <file relUrl="Content/Images/box-btm-four.png" publishTime="10/04/2011 22:47:07" />
    <file relUrl="Views/Demo/NExtra.ValidationAttributes.EmailAddressAttribute.cshtml" publishTime="10/04/2011 22:47:07" />
    <file relUrl="Scripts/Components/jquery.treeview/jquery.treeview.edit.js" publishTime="10/04/2011 22:47:07" />
    <file relUrl="Scripts/Components/jquery.watermark-3.0.6/changelog.txt" publishTime="10/04/2011 22:47:07" />
    <file relUrl="bin/NExtra.dll" publishTime="10/19/2011 22:59:11" />
    <file relUrl="Views/Demo/NExtra.Web.HttpContextCookieHandler.cshtml" publishTime="10/04/2011 22:47:07" />
    <file relUrl="Scripts/Components/jquery.treeview/demo/demo.js" publishTime="10/04/2011 22:47:07" />
    <file relUrl="Scripts/Components/jquery.treeview/demo/images.html" publishTime="10/04/2011 22:47:07" />
    <file relUrl="Content/Images/box-top-two.png" publishTime="10/04/2011 22:47:07" />
    <file relUrl="Views/Demo/NExtra.Extensions.IQueryableExtensions.cshtml" publishTime="10/04/2011 22:47:07" />
    <file relUrl="Views/Demo/NExtra.Email.EmailNonSender.cshtml" publishTime="10/04/2011 22:47:07" />
    <file relUrl="bin/NExtra.Web.pdb" publishTime="10/19/2011 22:59:13" />
    <file relUrl="Content/Images/favicon.ico" publishTime="10/04/2011 22:47:07" />
    <file relUrl="Views/Demo/NExtra.Mvc.HtmlHelpers.GlobalResourceHelper.cshtml" publishTime="10/04/2011 22:47:07" />
    <file relUrl="Scripts/Components/jquery.treeview/demo/screen.css" publishTime="10/04/2011 22:47:07" />
    <file relUrl="Scripts/Components/jquery.treeview/images/treeview-default-line.gif" publishTime="10/04/2011 22:47:07" />
    <file relUrl="Scripts/jquery-1.4.4.min.js" publishTime="10/04/2011 22:47:07" />
    <file relUrl="Views/Demo/NExtra.Web.ResponseFilters.Html5ElementConvertFilter.cshtml" publishTime="10/04/2011 22:47:07" />
    <file relUrl="Global.asax" publishTime="10/04/2011 22:47:07" />
    <file relUrl="Views/Demo/App_LocalResources/NExtra.Mvc.HtmlHelpers.ResourceStringHelper.cshtml.resx" publishTime="10/04/2011 22:47:07" />
    <file relUrl="Content/Images/box-top-three.png" publishTime="10/04/2011 22:47:07" />
    <file relUrl="Scripts/Components/jquery.treeview/demo/sortable.html" publishTime="10/04/2011 22:47:07" />
    <file relUrl="Content/Images/box-btm-three.png" publishTime="10/04/2011 22:47:07" />
    <file relUrl="Scripts/MicrosoftMvcValidation.js" publishTime="10/04/2011 22:47:07" />
    <file relUrl="Views/Demo/NExtra.Geo.AngleConverter.cshtml" publishTime="10/04/2011 22:47:07" />
    <file relUrl="Views/Demo/NExtra.ValidationAttributes.UrlAttribute.cshtml" publishTime="10/04/2011 22:47:07" />
    <file relUrl="Content/Images/box-btm-six.png" publishTime="10/04/2011 22:47:07" />
    <file relUrl="Scripts/MicrosoftMvcValidation.debug.js" publishTime="10/04/2011 22:47:07" />
    <file relUrl="Views/Demo/NExtra.Extensions.ObjectExtensions.cshtml" publishTime="10/04/2011 22:47:07" />
    <file relUrl="Views/Demo/NExtra.Documentation.XmlDocumentationHandler_Type.cshtml" publishTime="10/04/2011 22:47:07" />
    <file relUrl="Scripts/Components/jquery.treeview/demo/large.html" publishTime="10/04/2011 22:47:07" />
    <file relUrl="Content/Images/bg-lines-soft.png" publishTime="10/04/2011 22:47:07" />
    <file relUrl="Content/Images/box-btm.png" publishTime="10/04/2011 22:47:07" />
    <file relUrl="Scripts/Components/jquery.watermark-3.0.6/jquery.watermark.js" publishTime="10/04/2011 22:47:07" />
    <file relUrl="Scripts/Components/jquery.treeview/images/treeview-default.gif" publishTime="10/04/2011 22:47:07" />
    <file relUrl="Scripts/Components/jquery.treeview/jquery.treeview.async.js" publishTime="10/04/2011 22:47:07" />
    <file relUrl="Views/Demo/NExtra.Extensions.StringCollectionExtensions.cshtml" publishTime="10/04/2011 22:47:07" />
    <file relUrl="Content/Images/box-btm-two.png" publishTime="10/04/2011 22:47:07" />
    <file relUrl="Views/Demo/NExtra.Extensions.IComparableExtensions.cshtml" publishTime="10/04/2011 22:47:07" />
    <file relUrl="Scripts/Components/jquery.treeview/jquery.treeview.css" publishTime="10/04/2011 22:47:07" />
    <file relUrl="bin/NExtra.Mvc.dll" publishTime="10/19/2011 22:59:12" />
    <file relUrl="Views/Demo/NExtra.Mvc.Extensions.ControllerExtensions.cshtml" publishTime="10/04/2011 22:47:07" />
    <file relUrl="Scripts/Components/jquery.treeview/images/file.gif" publishTime="10/04/2011 22:47:07" />
    <file relUrl="Views/Demo/NExtra.Extensions.EnumExtensions.cshtml" publishTime="10/04/2011 22:47:07" />
    <file relUrl="Views/Demo/NExtra.Mvc.HtmlHelpers.LocalResourceHelper.cshtml" publishTime="10/04/2011 22:47:07" />
    <file relUrl="Views/Demo/NExtra.Web.Security.Md5Generator.cshtml" publishTime="10/04/2011 22:47:07" />
    <file relUrl="Views/_ViewStart.cshtml" publishTime="10/04/2011 22:47:07" />
    <file relUrl="Views/Demo/NExtra.Web.HttpModules.Html5ElementConvertModule.cshtml" publishTime="10/04/2011 22:47:07" />
    <file relUrl="Scripts/Components/jquery.treeview/demo/prerendered.html" publishTime="10/04/2011 22:47:07" />
    <file relUrl="Views/Demo/NExtra.Extensions.StructExtensions.cshtml" publishTime="10/04/2011 22:47:07" />
    <file relUrl="Views/Home/Index.cshtml" publishTime="10/04/2011 22:47:07" />
    <file relUrl="Scripts/Components/jquery.treeview/images/treeview-red.gif" publishTime="10/04/2011 22:47:07" />
    <file relUrl="App_GlobalResources/Language.resx" publishTime="10/04/2011 22:47:07" />
    <file relUrl="Scripts/Components/jquery.watermark-3.0.6/jquery.watermark.htm" publishTime="10/04/2011 22:47:07" />
    <file relUrl="Scripts/Components/jquery.treeview/lib/jquery.cookie.js" publishTime="10/04/2011 22:47:07" />
    <file relUrl="Scripts/jquery.validate-vsdoc.js" publishTime="10/04/2011 22:47:07" />
    <file relUrl="Views/Demo/NExtra.Web.HtmlReplacer.cshtml" publishTime="10/04/2011 22:47:07" />
    <file relUrl="Views/Demo/NExtra.Documentation.XmlDocumentationHandler_MethodInfo.cshtml" publishTime="10/04/2011 22:47:07" />
    <file relUrl="Scripts/MicrosoftMvcAjax.js" publishTime="10/04/2011 22:47:07" />
    <file relUrl="bin/NExtra.Mvc.xml" publishTime="10/19/2011 22:59:12" />
    <file relUrl="Content/Images/box-top.png" publishTime="10/04/2011 22:47:07" />
    <file relUrl="Content/Images/logo.png" publishTime="10/04/2011 22:47:07" />
    <file relUrl="Views/Demo/NExtra.Documentation.XmlDocumentationHandler_Assembly.cshtml" publishTime="10/04/2011 22:47:07" />
    <file relUrl="Views/Demo/NExtra.Web.Extensions.StateBagExtensions.cshtml" publishTime="10/04/2011 22:47:07" />
    <file relUrl="Scripts/Components/jquery.treeview/demo/edit.html" publishTime="10/04/2011 22:47:07" />
    <file relUrl="Views/Demo/App_LocalResources/Index.cshtml.resx" publishTime="10/04/2011 22:47:07" />
    <file relUrl="Views/Demo/NExtra.ValidationAttributes.GuidAttribute.cshtml" publishTime="10/04/2011 22:47:07" />
    <file relUrl="Views/Shared/_Layout.cshtml" publishTime="10/04/2011 22:47:07" />
    <file relUrl="Content/Images/box-btm-five.png" publishTime="10/04/2011 22:47:07" />
    <file relUrl="Scripts/Components/jquery.treeview/demo/bg.gif" publishTime="10/04/2011 22:47:07" />
    <file relUrl="Scripts/Components/jquery.watermark-3.0.6/mit-license.txt" publishTime="10/04/2011 22:47:07" />
    <file relUrl="Views/Demo/NExtra.Testing.CrossThreadTestRunner.cshtml" publishTime="10/04/2011 22:47:07" />
    <file relUrl="Scripts/Components/jquery.treeview/images/treeview-famfamfam.gif" publishTime="10/04/2011 22:47:07" />
    <file relUrl="Content/Images/ul-clean-bg.png" publishTime="10/04/2011 22:47:07" />
    <file relUrl="Views/Demo/NExtra.Web.Security.Sha1Generator.cshtml" publishTime="10/04/2011 22:47:07" />
    <file relUrl="Scripts/Components/jquery.treeview/lib/jquery.js" publishTime="10/04/2011 22:47:07" />
    <file relUrl="Content/Images/bg-lines.gif" publishTime="10/04/2011 22:47:07" />
    <file relUrl="bin/NExtra.Web.xml" publishTime="10/19/2011 22:59:12" />
    <file relUrl="Views/Demo/NExtra.Pagination.PaginationContext.cshtml" publishTime="10/04/2011 22:47:07" />
    <file relUrl="Scripts/jquery-1.4.1-vsdoc.js" publishTime="10/04/2011 22:47:07" />
    <file relUrl="Views/Demo/NExtra.Documentation.XmlDocumentationHandler.cshtml" publishTime="10/04/2011 22:47:07" />
    <file relUrl="Views/Demo/NExtra.Extensions.XmlElementExtensions.cshtml" publishTime="10/04/2011 22:47:07" />
    <file relUrl="Scripts/Components/jquery.treeview/demo/simple.html" publishTime="10/04/2011 22:47:07" />
    <file relUrl="Views/Demo/NExtra.Web.Security.MembershipFacade.cshtml" publishTime="10/04/2011 22:47:07" />
    <file relUrl="Scripts/Components/jquery.treeview/changelog.txt" publishTime="10/04/2011 22:47:07" />
    <file relUrl="bin/NExtra.Demo.pdb" publishTime="10/20/2011 00:02:38" />
    <file relUrl="bin/NExtra.pdb" publishTime="10/19/2011 22:59:11" />
    <file relUrl="Views/Demo/NExtra.Mvc.Testing.ControllerExtensions.cshtml" publishTime="10/04/2011 22:47:07" />
    <file relUrl="Scripts/MicrosoftAjax.debug.js" publishTime="10/04/2011 22:47:07" />
    <file relUrl="Scripts/Components/jquery.treeview/images/treeview-black-line.gif" publishTime="10/04/2011 22:47:07" />
    <file relUrl="Views/Demo/NExtra.Nullable.cshtml" publishTime="10/04/2011 22:47:07" />
    <file relUrl="Views/Demo/Index.cshtml" publishTime="10/04/2011 22:47:07" />
    <file relUrl="Views/Demo/NExtra.Extensions.IEnumerableExtensions.cshtml" publishTime="10/04/2011 22:47:07" />
    <file relUrl="Content/Images/a-bg.png" publishTime="10/04/2011 22:47:07" />
    <file relUrl="Views/Demo/NExtra.ValidationAttributes.SwedishSsnAttribute.cshtml" publishTime="10/04/2011 22:47:07" />
    <file relUrl="bin/NExtra.Web.dll" publishTime="10/19/2011 22:59:13" />
    <file relUrl="Scripts/Components/jquery.treeview/images/treeview-famfamfam-line.gif" publishTime="10/04/2011 22:47:07" />
    <file relUrl="Views/Demo/NExtra.Mvc.ActionFilters.OutputModelAttribute.cshtml" publishTime="10/04/2011 22:47:07" />
    <file relUrl="Views/Demo/NExtra.Web.SyndicationFeedLoader.cshtml" publishTime="10/04/2011 22:47:07" />
    <file relUrl="Content/Css/main.css" publishTime="10/04/2011 22:47:07" />
    <file relUrl="Scripts/Components/jquery.treeview/demo/index.html" publishTime="10/04/2011 22:47:07" />
    <file relUrl="Scripts/Components/jquery.watermark-3.0.6/jquery.watermark.min.js" publishTime="10/04/2011 22:47:07" />
    <file relUrl="Scripts/Components/jquery.treeview/images/folder-closed.gif" publishTime="10/04/2011 22:47:07" />
    <file relUrl="Content/Css/classes.css" publishTime="10/04/2011 22:47:07" />
    <file relUrl="Views/Demo/NExtra.Web.HtmlRemover.cshtml" publishTime="10/04/2011 22:47:07" />
    <file relUrl="Scripts/Components/jquery.treeview/jquery.treeview.js" publishTime="10/04/2011 22:47:07" />
    <file relUrl="Views/Demo/NExtra.Geo.Position.cshtml" publishTime="10/04/2011 22:47:07" />
    <file relUrl="Scripts/Components/jquery.treeview/images/treeview-black.gif" publishTime="10/04/2011 22:47:07" />
    <file relUrl="Views/Demo/NExtra.DataAnnotations.OptionalRegularExpressionAttribute.cshtml" publishTime="10/04/2011 22:47:07" />
    <file relUrl="Scripts/jquery.validate.min.js" publishTime="10/04/2011 22:47:07" />
    <file relUrl="Scripts/Components/jquery.treeview/images/ajax-loader.gif" publishTime="10/04/2011 22:47:07" />
    <file relUrl="bin/NExtra.xml" publishTime="10/19/2011 22:59:11" />
    <file relUrl="Views/Demo/NExtra.EventArgs.cshtml" publishTime="10/04/2011 22:47:07" />
    <file relUrl="Views/Demo/NExtra.Web.Security.FormsAuthenticationFacade.cshtml" publishTime="10/04/2011 22:47:07" />
    <file relUrl="Scripts/Components/jquery.treeview/jquery.treeview.sortable.js" publishTime="10/04/2011 22:47:07" />
    <file relUrl="Scripts/Components/jquery.watermark-3.0.6/gpl2-license.txt" publishTime="10/04/2011 22:47:07" />
    <file relUrl="Views/Demo/NExtra.Extensions.UriExtensions.cshtml" publishTime="10/04/2011 22:47:07" />
    <file relUrl="Scripts/Components/jquery.treeview/images/treeview-gray-line.gif" publishTime="10/04/2011 22:47:07" />
    <file relUrl="Views/Demo/NExtra.Web.Html5ElementSupport.cshtml" publishTime="10/04/2011 22:47:07" />
    <file relUrl="Views/Demo/NExtra.Geo.PositionHandler.cshtml" publishTime="10/04/2011 22:47:07" />
  </publishProfile>
</publishData>